resolvematrix/__init__.py
resolvematrix/__main__.py
resolvematrix/__version__.py
resolvematrix/cache.py
resolvematrix/client.py
resolvematrix/err.py
resolvematrix/server.py
resolvematrix/test_resolver.py
resolvematrix-1.0.0.dist-info/licenses/LICENSE
resolvematrix-1.0.0.dist-info/METADATA
resolvematrix-1.0.0.dist-info/WHEEL
resolvematrix-1.0.0.dist-info/entry_points.txt
resolvematrix-1.0.0.dist-info/top_level.txt
resolvematrix-1.0.0.dist-info/RECORD
