Metadata-Version: 2.4
Name: resolvematrix
Version: 1.0.0
Summary: Matrix server resolver library for Python
Author-email: Nexus <pip@nexy7574.co.uk>
License-Expression: MPL-2.0
Project-URL: Source, https://codeberg.org/timedout/resolvematrix
Project-URL: Tracker, https://codeberg.org/timedout/resolvematrix/issues
Project-URL: Matrix Room, https://matrix.to/#/#ontopic:timedout.uk
Project-URL: Funding, https://ko-fi.com/nexy7574
Classifier: Development Status :: 5 - Production/Stable
Classifier: Intended Audience :: Developers
Classifier: Natural Language :: English
Classifier: Operating System :: Microsoft :: Windows
Classifier: Operating System :: POSIX
Classifier: Programming Language :: Python :: 3 :: Only
Classifier: Programming Language :: Python :: 3.10
Classifier: Programming Language :: Python :: 3.11
Classifier: Programming Language :: Python :: 3.12
Classifier: Programming Language :: Python :: 3.13
Classifier: Programming Language :: Python :: Implementation :: CPython
Classifier: Topic :: Communications
Classifier: Topic :: Internet
Classifier: Topic :: Software Development :: Libraries
Classifier: Topic :: Software Development :: Libraries :: Application Frameworks
Classifier: Topic :: Utilities
Requires-Python: <3.14,>=3.10
License-File: LICENSE
Requires-Dist: httpx~=0.28
Requires-Dist: dnspython~=2.7
Requires-Dist: pydantic~=2.11
Provides-Extra: dev
Requires-Dist: pytest~=8.4; extra == "dev"
Requires-Dist: twine~=6.1; extra == "dev"
Requires-Dist: build~=1.3; extra == "dev"
Dynamic: license-file
